{"trial_id": "0005", "hyperparameters": {"space": [{"class_name": "Choice", "config": {"name": "kernel_regularizer", "default": 0.001, "conditions": [], "values": [0.001, 0.01, 0.1], "ordered": true}}, {"class_name": "Choice", "config": {"name": "learning_rate", "default": 0.001, "conditions": [], "values": [0.001, 0.0005, 0.0001], "ordered": true}}, {"class_name": "Choice", "config": {"name": "optimizer", "default": "adam", "conditions": [], "values": ["adam", "rmsprop", "sgd"], "ordered": false}}], "values": {"kernel_regularizer": 0.001, "learning_rate": 0.001, "optimizer": "adam", "tuner/epochs": 2, "tuner/initial_epoch": 0, "tuner/bracket": 3, "tuner/round": 0}}, "metrics": {"metrics": {"loss": {"direction": "min", "observations": [{"value": [0.273436576128006], "step": 1}]}, "val_loss": {"direction": "min", "observations": [{"value": [0.2571823298931122], "step": 1}]}}}, "score": 0.2571823298931122, "best_step": 1, "status": "COMPLETED", "message": null}